[{"nom":"Dissay","s22a":767053},{"nom":"Availles-en-Châtellerault","s22a":55422},{"nom":"Croutelle","s22a":0},{"nom":"Sanxay","s22a":933406},{"nom":"Chasseneuil-du-Poitou","s22a":1926520},{"nom":"Sainte-Radégonde","s22a":0},{"nom":"Jardres","s22a":0},{"nom":"Bonneuil-Matours","s22a":7977045},{"nom":"Vouneuil-sur-Vienne","s22a":975161},{"nom":"Montamisé","s22a":0},{"nom":"Lavoux","s22a":0},{"nom":"Bellefonds","s22a":351280},{"nom":"Sèvres-Anxaumont","s22a":0},{"nom":"Cenon-sur-Vienne","s22a":1413152},{"nom":"Curzay-sur-Vonne","s22a":306182},{"nom":"Bignoux","s22a":0},{"nom":"Rouillé","s22a":0},{"nom":"Chauvigny","s22a":8961987},{"nom":"Valdivienne","s22a":8974055},{"nom":"La Puye","s22a":0},{"nom":"La Chapelle-Moulière","s22a":398697},{"nom":"Liniers","s22a":0},{"nom":"Saint-Julien-l'Ars","s22a":0},{"nom":"Bonnes","s22a":4352433},{"nom":"Béruges","s22a":597490},{"nom":"Ligugé","s22a":2353081},{"nom":"Poitiers","s22a":62462045},{"nom":"Biard","s22a":271972},{"nom":"Migné-Auxances","s22a":2016008},{"nom":"Châtellerault","s22a":11287569},{"nom":"Buxerolles","s22a":1182154},{"nom":"Naintré","s22a":6200223},{"nom":"Lusignan","s22a":282153},{"nom":"Beaumont Saint-Cyr","s22a":632164},{"nom":"Jaunay-Marigny","s22a":7567875},{"nom":"Saint-Benoît","s22a":3625836},{"nom":"Jazeneuil","s22a":412001},{"nom":"Saint-Georges-lès-Baillargeaux","s22a":38719},{"nom":"Saint-Sauvant","s22a":0},{"nom":"Celle-Lévescault","s22a":151219},{"nom":"Savigny-Lévescault","s22a":0},{"nom":"Pouillé","s22a":0},{"nom":"Mignaloux-Beauvoir","s22a":0},{"nom":"Tercé","s22a":0},{"nom":"Cloué","s22a":311747},{"nom":"Smarves","s22a":1274617},{"nom":"Vouneuil-sous-Biard","s22a":95329},{"nom":"Fontaine-le-Comte","s22a":0},{"nom":"Coulombiers","s22a":0}]
