[{"nom":"Dissay","s25c":0},{"nom":"Availles-en-Châtellerault","s25c":0},{"nom":"Croutelle","s25c":0},{"nom":"Sanxay","s25c":0},{"nom":"Chasseneuil-du-Poitou","s25c":0},{"nom":"Sainte-Radégonde","s25c":0},{"nom":"Jardres","s25c":0},{"nom":"Bonneuil-Matours","s25c":0.32},{"nom":"Vouneuil-sur-Vienne","s25c":0},{"nom":"Montamisé","s25c":0},{"nom":"Lavoux","s25c":0},{"nom":"Bellefonds","s25c":1.7},{"nom":"Sèvres-Anxaumont","s25c":0},{"nom":"Cenon-sur-Vienne","s25c":0},{"nom":"Curzay-sur-Vonne","s25c":0},{"nom":"Bignoux","s25c":0},{"nom":"Rouillé","s25c":0},{"nom":"Chauvigny","s25c":0},{"nom":"Valdivienne","s25c":0},{"nom":"La Puye","s25c":0},{"nom":"La Chapelle-Moulière","s25c":0},{"nom":"Liniers","s25c":0},{"nom":"Saint-Julien-l'Ars","s25c":0},{"nom":"Bonnes","s25c":4.27},{"nom":"Béruges","s25c":0},{"nom":"Ligugé","s25c":0},{"nom":"Poitiers","s25c":0},{"nom":"Biard","s25c":0},{"nom":"Migné-Auxances","s25c":0},{"nom":"Châtellerault","s25c":0},{"nom":"Buxerolles","s25c":0},{"nom":"Naintré","s25c":0},{"nom":"Lusignan","s25c":0},{"nom":"Beaumont Saint-Cyr","s25c":0},{"nom":"Jaunay-Marigny","s25c":0},{"nom":"Saint-Benoît","s25c":0},{"nom":"Jazeneuil","s25c":0},{"nom":"Saint-Georges-lès-Baillargeaux","s25c":0},{"nom":"Saint-Sauvant","s25c":0},{"nom":"Celle-Lévescault","s25c":0},{"nom":"Savigny-Lévescault","s25c":0},{"nom":"Pouillé","s25c":0},{"nom":"Mignaloux-Beauvoir","s25c":0},{"nom":"Tercé","s25c":0},{"nom":"Cloué","s25c":0},{"nom":"Smarves","s25c":0},{"nom":"Vouneuil-sous-Biard","s25c":0},{"nom":"Fontaine-le-Comte","s25c":0},{"nom":"Coulombiers","s25c":0}]
